oauth2_capture/CHANGELOG.md
oauth2_capture/__init__.py
oauth2_capture/admin.py
oauth2_capture/apps.py
oauth2_capture/exceptions.py
oauth2_capture/models.py
oauth2_capture/urls.py
oauth2_capture/views.py
oauth2_capture/migrations/0001_initial.py
oauth2_capture/migrations/0002_alter_oauthtoken_access_token.py
oauth2_capture/migrations/__init__.py
oauth2_capture/services/__init__.py
oauth2_capture/services/oauth2.py
oauth2_capture/templates/oauth2_capture/base.html
oauth2_capture/templates/oauth2_capture/callback_success.html
oauth2_capture/templates/oauth2_capture/oauthtoken_confirm_delete.html
oauth2_capture/templates/oauth2_capture/oauthtoken_list.html
oauth2_capture/tests/__init__.py
oauth2_capture/tests/test_token_refresh.py
oauth2_capture/tests/test_views.py
oauth2_capture/tests/services/__init__.py
oauth2_capture/tests/services/oauth2/__init__.py
oauth2_capture/tests/services/oauth2/test_retry_with_backoff.py
oauth2_capture-0.6.0.dist-info/METADATA
oauth2_capture-0.6.0.dist-info/WHEEL
oauth2_capture-0.6.0.dist-info/licenses/LICENSE
oauth2_capture-0.6.0.dist-info/RECORD
