Metadata-Version: 2.4
Name: oauth2_capture
Version: 0.6.0
Summary: Capture and store OAuth2 tokens for later use.
Project-URL: Home, https://github.com/heysamtexas/django-oauth2-capture
Project-URL: Documentation, https://github.com/heysamtexas/django-oauth2-capture#readme
Project-URL: Source, https://github.com/heysamtexas/django-oauth2-capture
Project-URL: Issues, https://github.com/heysamtexas/django-oauth2-capture#readme/issues
Author-email: Sam Texas <github+oauth2_capture@simplecto.com>
License-File: LICENSE
Classifier: Development Status :: 4 - Beta
Classifier: Intended Audience :: Developers
Classifier: License :: OSI Approved :: MIT License
Classifier: Programming Language :: Python :: 3
Classifier: Programming Language :: Python :: 3.8
Classifier: Programming Language :: Python :: 3.9
Classifier: Programming Language :: Python :: 3.10
Classifier: Programming Language :: Python :: 3.11
Classifier: Programming Language :: Python :: 3.12
Requires-Python: >=3.12
Requires-Dist: django-environ
Requires-Dist: django>=4.2
Requires-Dist: requests~=2.32.4
Requires-Dist: shortuuid==1.0.13
Provides-Extra: dev
Requires-Dist: coverage[toml]<7.11,>=7.4; extra == 'dev'
Requires-Dist: pre-commit==4.3.0; extra == 'dev'
Requires-Dist: ruff==0.12.8; extra == 'dev'
